README.rst
setup.cfg
setup.py
csv2json/__init__.py
csv2json/csv2json.py
csv2json/main.py
csv_2_json.egg-info/PKG-INFO
csv_2_json.egg-info/SOURCES.txt
csv_2_json.egg-info/dependency_links.txt
csv_2_json.egg-info/entry_points.txt
csv_2_json.egg-info/top_level.txt