Metadata-Version: 1.2
Name: csv_2_json
Version: 1.0.1
Summary: A tool for csv to json file conversion
Home-page: https://github.com/zWaR/csv2json
Author: zWaR
Author-email: zwar@sharklasers.com
License: UNKNOWN
Project-URL: Source Code, https://github.com/zWaR/csv2json.git
Project-URL: Bug Tracker, https://github.com/zWaR/csv2json/issues
Project-URL: Documentation, https://github.com/zWaR/csv2json
Keywords: csv json conversion tool
Platform: UNKNOWN
Classifier: Intended Audience :: Developers
Classifier: License :: OSI Approved :: MIT License
Classifier: Programming Language :: Python :: 3.6
